{
  "title": "miroslaw.ovh",
  "description": "Artykuły o programowaniu i Linuksie",
  "id": "https://miroslaw.ovh",
  "link": "https://miroslaw.ovh",
  "language": "pl",
  "image": "https://miroslaw.ovh/assets/img/logo.jpg",
  "favicon": "https://miroslaw.ovh/assets/img/logo.jpg",
  "copyright": "2021 miroslaw.ovh",
  "generator": "Artykuły o programowaniu i Linuksie",
  "filename": "feed",
  "feedLinks": {
    "json": "https://miroslaw.ovh/feed.json",
    "atom": "https://miroslaw.ovh/feed.atom",
    "xml": "https://miroslaw.ovh/feed.xml"
  },
  "outDir": "./dist/static",
  "categories": ["Web Development", "Blog", "Angular", "node"],
  "blogPostRouteSlug": "/blog",
  "newestPostsFirst": true
}
